<?xml version="1.0" encoding="utf-8"?>
<IncrementalBankBuild Version="6" Flags="1179865962">
	<Platform GUID="{E2C35059-2645-4487-B21B-A28C5B72CB25}">
		<Banks>
			<Language ID="393239870">
				<File Name="Cinematic_Level_2" Hash="3294363480" Timestamp="1590327598"/>
				<File Name="Geralt" Hash="1308259956" Timestamp="1590327598"/>
				<File Name="Human_enemies" Hash="2148875523" Timestamp="1590327598"/>
				<File Name="Init" Hash="830695076" Timestamp="1590327598"/>
				<File Name="Jaskier" Hash="242320945" Timestamp="1590327598"/>
				<File Name="Level_2" Hash="594059583" Timestamp="1590327598"/>
				<File Name="Main_menu" Hash="1386292246" Timestamp="1590327598"/>
				<File Name="Monster_enemies" Hash="2163539180" Timestamp="1590327598"/>
				<File Name="Music_Levels" Hash="4261954882" Timestamp="1590327598"/>
				<File Name="Music_Menus" Hash="3288945538" Timestamp="1590327598"/>
				<File Name="Pause_menu" Hash="3953933198" Timestamp="1590327598"/>
				<File Name="Props" Hash="1270310993" Timestamp="1590327598"/>
			</Language>
		</Banks>
		<XMLInfo>
			<Language ID="393239870">
				<File Name="Cinematic_Level_2" Hash="114414092" Timestamp="1590327598"/>
				<File Name="Geralt" Hash="1760692216" Timestamp="1590327598"/>
				<File Name="Human_enemies" Hash="1175741755" Timestamp="1590327598"/>
				<File Name="Init" Hash="1310669568" Timestamp="1590327598"/>
				<File Name="Jaskier" Hash="3293834318" Timestamp="1590327598"/>
				<File Name="Level_2" Hash="1189465392" Timestamp="1590327598"/>
				<File Name="Main_menu" Hash="3630575357" Timestamp="1590327598"/>
				<File Name="Monster_enemies" Hash="235511330" Timestamp="1590327598"/>
				<File Name="Music_Levels" Hash="12911643" Timestamp="1590327598"/>
				<File Name="Music_Menus" Hash="455445430" Timestamp="1590327598"/>
				<File Name="Pause_menu" Hash="1248011717" Timestamp="1590327598"/>
				<File Name="Props" Hash="2881480750" Timestamp="1590327598"/>
			</Language>
			<Language ID="-1">
				<File Name="" Hash="1520645241" Timestamp="1590327598"/>
			</Language>
		</XMLInfo>
		<JSONInfo>
			<Language ID="393239870">
				<File Name="Cinematic_Level_2" Hash="3186208091" Timestamp="1590327598"/>
				<File Name="Geralt" Hash="2858417304" Timestamp="1590327598"/>
				<File Name="Human_enemies" Hash="3191892263" Timestamp="1590327598"/>
				<File Name="Init" Hash="707144178" Timestamp="1590327598"/>
				<File Name="Jaskier" Hash="1519578673" Timestamp="1590327598"/>
				<File Name="Level_2" Hash="2349113598" Timestamp="1590327598"/>
				<File Name="Main_menu" Hash="4271754481" Timestamp="1590327598"/>
				<File Name="Monster_enemies" Hash="1030891674" Timestamp="1590327598"/>
				<File Name="Music_Levels" Hash="3731897015" Timestamp="1590327598"/>
				<File Name="Music_Menus" Hash="192088032" Timestamp="1590327598"/>
				<File Name="Pause_menu" Hash="2104627452" Timestamp="1590327598"/>
				<File Name="Props" Hash="4142958095" Timestamp="1590327598"/>
			</Language>
			<Language ID="-1">
				<File Name="" Hash="2255475442" Timestamp="1590327598"/>
			</Language>
		</JSONInfo>
	</Platform>
</IncrementalBankBuild>
